Workbook
Name Slicer_City: #N/A
Name Slicer_Department: #N/A
Name Slicer_PaymentMode: #N/A

Sheet Dashboard_Sheet
A1: Retail Sales Dashboard
B3: KPI 1 | T3: KPI 2
C4: Total Sales | U4: Payment mode
C5: =SUM(Formula_Analysis!M:M) -> 310002 | U5: =COUNTA(Cleaned_Data!A:A)-1 -> 19
C23: KPI 4
D24: Best city
D25: Delhi

Sheet Pivot_Reports
A1: OrderID | B1: Employee name | C1: Department | D1: City | E1: Product | F1: Category | G1: Quantity | H1: Price | I1: OrderDate | J1: PaymentMode | K1: Rating | L1: ManagerCode | M1: Total_sales
A2: OD101 | B2: Rahul Sharma | C2: Electronics | D2: Delhi | E2: Laptop | F2: Electronics | G2: 2 | H2: 55000 | I2: 46034 | J2: UPI | K2: 5 | L2: M101 | M2: =G2*H2 -> 110000
A3: OD102 | B3: Priya Mehta | C3: Fashion | D3: Mumbai | E3: Tshirt | F3: Fashion | G3: 5 | H3: 799 | I3: 46037 | J3: Cash | K3: 4 | L3: M102 | M3: =G3*H3 -> 3995
A4: OD103 | B4: Amit Verma | C4: Grocery | D4: Delhi | E4: Rice Bag | F4: Grocery | G4: 3 | H4: 1200 | I4: 46040 | J4: Card | K4: 3 | L4: M103 | M4: =G4*H4 -> 3600
A5: OD104 | B5: Neha Kapoor | C5: Electronics | D5: Pune | E5: Mouse | F5: Electronics | G5: 10 | H5: 599 | I5: 46042 | J5: UPI | K5: 5 | L5: M101 | M5: =G5*H5 -> 5990
A6: OD105 | B6: Rohit Singh | C6: Fashion | D6: Delhi | E6: Jeans | F6: Fashion | G6: 4 | H6: 1899 | I6: 46044 | J6: Cash | K6: 2 | L6: M102 | M6: =G6*H6 -> 7596
A7: OD106 | B7: Karan Malhotra | C7: Grocery | D7: Mumbai | E7: Sugar | F7: Grocery | G7: 6 | H7: 450 | I7: 46047 | J7: Card | K7: 4 | L7: M103 | M7: =G7*H7 -> 2700
A8: OD107 | B8: Pooja Arora | C8: Electronics | D8: Bangalore | E8: Keyboard | F8: Electronics | G8: 7 | H8: 999 | I8: 46049 | J8: UPI | K8: 5 | L8: M101 | M8: =G8*H8 -> 6993
A9: OD108 | B9: Anjali Gupta | C9: Fashion | D9: Delhi | E9: Shoes | F9: Fashion | G9: 2 | H9: 2499 | I9: 46050 | J9: Card | K9: 4 | L9: M102 | M9: =G9*H9 -> 4998
A10: OD109 | B10: Vikas Kumar | C10: Grocery | D10: Pune | E10: Wheat | F10: Grocery | G10: 8 | H10: 950 | I10: 46052 | J10: Cash | K10: 3 | L10: M103 | M10: =G10*H10 -> 7600
A11: OD110 | B11: Riya Sharma | C11: Electronics | D11: Delhi | E11: Monitor | F11: Electronics | G11: 1 | H11: 12500 | I11: 46054 | J11: UPI | K11: 5 | L11: M101 | M11: =G11*H11 -> 12500
A12: OD112 | B12: Simran Kaur | C12: Fashion | D12: Mumbai | E12: Jacket | F12: Fashion | G12: 3 | H12: 3499 | I12: 46057 | J12: Card | K12: 4 | L12: M102 | M12: =G12*H12 -> 10497
A13: OD113 | B13: Arjun Patel | C13: Grocery | D13: Bangalore | E13: Oil | F13: Grocery | G13: 5 | H13: 1800 | I13: 46059 | J13: Cash | K13: 5 | L13: M103 | M13: =G13*H13 -> 9000
... A20: OD120 | B20: Ritika Jain | C20: Electronics | D20: Delhi | E20: Camera | F20: Electronics | G20: 1 | H20: 45000 | I20: 46071 | J20: UPI | K20: 5 | L20: M101 | M20: =G20*H20 -> 45000
B25: Sales_by_Department | E25: Sales_by_City | H25: Average_rating_by_Department | K25: Payment_mode_wise_Sales
B26: Department | C26: Sum of Total_sales | E26: city | F26: Sum of Total_sales | H26: Department | I26: Sum of Rating | K26: PaymentMode | L26: Sum of Total_sales
B27: Electronics | C27: 239480 | E27: Bangalore | F27: 30990 | H27: Electronics | I27: 30 | K27: Card | L27: 30581
B28: Fashion | C28: 35872 | E28: Delhi | F28: 192480 | H28: Fashion | I28: 23 | K28: Cash | L28: 39941
B29: Grocery | C29: 34650 | E29: Mumbai | F29: 22992 | H29: Grocery | I29: 24 | K29: UPI | L29: 239480
B30: Grand Total | C30: 310002 | E30: Pune | F30: 63540 | H30: Grand Total | I30: 77 | K30: Grand Total | L30: 310002
E31: Grand Total | F31: 310002

Sheet Formula_Analysis
A1: OrderID | B1: Employee name | C1: Department | D1: City | E1: Product | F1: Category | G1: Quantity | H1: Price | I1: OrderDate | J1: PaymentMode | K1: Rating | L1: ManagerCode | M1: Total_sales | N1: Performance_status | O1: Employee_id_card | Q1: ManagerName | R1: Region | S1: ManagerName | T1: Region
A2: OD101 | B2: Rahul Sharma | C2: Electronics | D2: Delhi | E2: Laptop | F2: Electronics | G2: 2 | H2: 55000 | I2: 46034 | J2: UPI | K2: 5 | L2: M101 | M2: =G2*H2 -> 110000 | N2: {=IF(K2:K20>=4,"Good","Poor")} -> Good | O2: =CONCATENATE(B2,"-",C2,"-",D2,"") -> Rahul Sharma-Electronics-Delhi | Q2: =VLOOKUP(L2,Manager_Data!A:C,2,FALSE) -> Aman Khanna | R2: =VLOOKUP(L2,Manager_Data!A:C,3,FALSE) -> North | S2: =_xlfn.XLOOKUP(L2,Manager_Data!A:A,Manager_Data!B:B,"no found") -> Aman Khanna | T2: {=_xlfn.XLOOKUP(L2:L20,Manager_Data!A:A,Manager_Data!C:C,"no found")} -> North
A3: OD102 | B3: Priya Mehta | C3: Fashion | D3: Mumbai | E3: Tshirt | F3: Fashion | G3: 5 | H3: 799 | I3: 46037 | J3: Cash | K3: 4 | L3: M102 | M3: =G3*H3 -> 3995 | N3: Good | O3: =CONCATENATE(B3,"-",C3,"-",D3,"") -> Priya Mehta-Fashion-Mumbai | Q3: =VLOOKUP(L3,Manager_Data!A:C,2,FALSE) -> Sneha Verma | R3: =VLOOKUP(L3,Manager_Data!A:C,3,FALSE) -> West | S3: =_xlfn.XLOOKUP(L3,Manager_Data!A:A,Manager_Data!B:B,"no found") -> Sneha Verma | T3: West
A4: OD103 | B4: Amit Verma | C4: Grocery | D4: Delhi | E4: Rice Bag | F4: Grocery | G4: 3 | H4: 1200 | I4: 46040 | J4: Card | K4: 3 | L4: M103 | M4: =G4*H4 -> 3600 | N4: Poor | O4: =CONCATENATE(B4,"-",C4,"-",D4,"") -> Amit Verma-Grocery-Delhi | Q4: =VLOOKUP(L4,Manager_Data!A:C,2,FALSE) -> Rajat Malhotra | R4: =VLOOKUP(L4,Manager_Data!A:C,3,FALSE) -> Central | S4: =_xlfn.XLOOKUP(L4,Manager_Data!A:A,Manager_Data!B:B,"no found") -> Rajat Malhotra | T4: Central
A5: OD104 | B5: Neha Kapoor | C5: Electronics | D5: Pune | E5: Mouse | F5: Electronics | G5: 10 | H5: 599 | I5: 46042 | J5: UPI | K5: 5 | L5: M101 | M5: =G5*H5 -> 5990 | N5: Good | O5: =CONCATENATE(B5,"-",C5,"-",D5,"") -> Neha Kapoor-Electronics-Pune | Q5: =VLOOKUP(L5,Manager_Data!A:C,2,FALSE) -> Aman Khanna | R5: =VLOOKUP(L5,Manager_Data!A:C,3,FALSE) -> North | S5: =_xlfn.XLOOKUP(L5,Manager_Data!A:A,Manager_Data!B:B,"no found") -> Aman Khanna | T5: North
A6: OD105 | B6: Rohit Singh | C6: Fashion | D6: Delhi | E6: Jeans | F6: Fashion | G6: 4 | H6: 1899 | I6: 46044 | J6: Cash | K6: 2 | L6: M102 | M6: =G6*H6 -> 7596 | N6: Poor | O6: =CONCATENATE(B6,"-",C6,"-",D6,"") -> Rohit Singh-Fashion-Delhi | Q6: =VLOOKUP(L6,Manager_Data!A:C,2,FALSE) -> Sneha Verma | R6: =VLOOKUP(L6,Manager_Data!A:C,3,FALSE) -> West | S6: =_xlfn.XLOOKUP(L6,Manager_Data!A:A,Manager_Data!B:B,"no found") -> Sneha Verma | T6: West
A7: OD106 | B7: Karan Malhotra | C7: Grocery | D7: Mumbai | E7: Sugar | F7: Grocery | G7: 6 | H7: 450 | I7: 46047 | J7: Card | K7: 4 | L7: M103 | M7: =G7*H7 -> 2700 | N7: Good | O7: =CONCATENATE(B7,"-",C7,"-",D7,"") -> Karan Malhotra-Grocery-Mumbai | Q7: =VLOOKUP(L7,Manager_Data!A:C,2,FALSE) -> Rajat Malhotra | R7: =VLOOKUP(L7,Manager_Data!A:C,3,FALSE) -> Central | S7: =_xlfn.XLOOKUP(L7,Manager_Data!A:A,Manager_Data!B:B,"no found") -> Rajat Malhotra | T7: Central
A8: OD107 | B8: Pooja Arora | C8: Electronics | D8: Bangalore | E8: Keyboard | F8: Electronics | G8: 7 | H8: 999 | I8: 46049 | J8: UPI | K8: 5 | L8: M101 | M8: =G8*H8 -> 6993 | N8: Good | O8: =CONCATENATE(B8,"-",C8,"-",D8,"") -> Pooja Arora-Electronics-Bangalore | Q8: =VLOOKUP(L8,Manager_Data!A:C,2,FALSE) -> Aman Khanna | R8: =VLOOKUP(L8,Manager_Data!A:C,3,FALSE) -> North | S8: =_xlfn.XLOOKUP(L8,Manager_Data!A:A,Manager_Data!B:B,"no found") -> Aman Khanna | T8: North
A9: OD108 | B9: Anjali Gupta | C9: Fashion | D9: Delhi | E9: Shoes | F9: Fashion | G9: 2 | H9: 2499 | I9: 46050 | J9: Card | K9: 4 | L9: M102 | M9: =G9*H9 -> 4998 | N9: Good | O9: =CONCATENATE(B9,"-",C9,"-",D9,"") -> Anjali Gupta-Fashion-Delhi | Q9: =VLOOKUP(L9,Manager_Data!A:C,2,FALSE) -> Sneha Verma | R9: =VLOOKUP(L9,Manager_Data!A:C,3,FALSE) -> West | S9: =_xlfn.XLOOKUP(L9,Manager_Data!A:A,Manager_Data!B:B,"no found") -> Sneha Verma | T9: West
A10: OD109 | B10: Vikas Kumar | C10: Grocery | D10: Pune | E10: Wheat | F10: Grocery | G10: 8 | H10: 950 | I10: 46052 | J10: Cash | K10: 3 | L10: M103 | M10: =G10*H10 -> 7600 | N10: Poor | O10: =CONCATENATE(B10,"-",C10,"-",D10,"") -> Vikas Kumar-Grocery-Pune | Q10: =VLOOKUP(L10,Manager_Data!A:C,2,FALSE) -> Rajat Malhotra | R10: =VLOOKUP(L10,Manager_Data!A:C,3,FALSE) -> Central | S10: =_xlfn.XLOOKUP(L10,Manager_Data!A:A,Manager_Data!B:B,"no found") -> Rajat Malhotra | T10: Central
A11: OD110 | B11: Riya Sharma | C11: Electronics | D11: Delhi | E11: Monitor | F11: Electronics | G11: 1 | H11: 12500 | I11: 46054 | J11: UPI | K11: 5 | L11: M101 | M11: =G11*H11 -> 12500 | N11: Good | O11: =CONCATENATE(B11,"-",C11,"-",D11,"") -> Riya Sharma-Electronics-Delhi | Q11: =VLOOKUP(L11,Manager_Data!A:C,2,FALSE) -> Aman Khanna | R11: =VLOOKUP(L11,Manager_Data!A:C,3,FALSE) -> North | S11: =_xlfn.XLOOKUP(L11,Manager_Data!A:A,Manager_Data!B:B,"no found") -> Aman Khanna | T11: North
A12: OD112 | B12: Simran Kaur | C12: Fashion | D12: Mumbai | E12: Jacket | F12: Fashion | G12: 3 | H12: 3499 | I12: 46057 | J12: Card | K12: 4 | L12: M102 | M12: =G12*H12 -> 10497 | N12: Good | O12: =CONCATENATE(B12,"-",C12,"-",D12,"") -> Simran Kaur-Fashion-Mumbai | Q12: =VLOOKUP(L12,Manager_Data!A:C,2,FALSE) -> Sneha Verma | R12: =VLOOKUP(L12,Manager_Data!A:C,3,FALSE) -> West | S12: =_xlfn.XLOOKUP(L12,Manager_Data!A:A,Manager_Data!B:B,"no found") -> Sneha Verma | T12: West
A13: OD113 | B13: Arjun Patel | C13: Grocery | D13: Bangalore | E13: Oil | F13: Grocery | G13: 5 | H13: 1800 | I13: 46059 | J13: Cash | K13: 5 | L13: M103 | M13: =G13*H13 -> 9000 | N13: Good | O13: =CONCATENATE(B13,"-",C13,"-",D13,"") -> Arjun Patel-Grocery-Bangalore | Q13: =VLOOKUP(L13,Manager_Data!A:C,2,FALSE) -> Rajat Malhotra | R13: =VLOOKUP(L13,Manager_Data!A:C,3,FALSE) -> Central | S13: =_xlfn.XLOOKUP(L13,Manager_Data!A:A,Manager_Data!B:B,"no found") -> Rajat Malhotra | T13: Central
A14: OD114 | B14: Meena Joshi | C14: Electronics | D14: Pune | E14: Tablet | F14: Electronics | G14: 2 | H14: 22000 | I14: 46060 | J14: UPI | K14: 3 | L14: M101 | M14: =G14*H14 -> 44000 | N14: Poor | O14: =CONCATENATE(B14,"-",C14,"-",D14,"") -> Meena Joshi-Electronics-Pune | Q14: =VLOOKUP(L14,Manager_Data!A:C,2,FALSE) -> Aman Khanna | R14: =VLOOKUP(L14,Manager_Data!A:C,3,FALSE) -> North | S14: =_xlfn.XLOOKUP(L14,Manager_Data!A:A,Manager_Data!B:B,"no found") -> Aman Khanna | T14: North
... A20: OD120 | B20: Ritika Jain | C20: Electronics | D20: Delhi | E20: Camera | F20: Electronics | G20: 1 | H20: 45000 | I20: 46071 | J20: UPI | K20: 5 | L20: M101 | M20: =G20*H20 -> 45000 | N20: Good | O20: =CONCATENATE(B20,"-",C20,"-",D20,"") -> Ritika Jain-Electronics-Delhi | Q20: =VLOOKUP(L20,Manager_Data!A:C,2,FALSE) -> Aman Khanna | R20: =VLOOKUP(L20,Manager_Data!A:C,3,FALSE) -> North | S20: =_xlfn.XLOOKUP(L20,Manager_Data!A:A,Manager_Data!B:B,"no found") -> Aman Khanna | T20: North
M21: some formulas work | Q21: lookup_function
A25: summary section
A29: Total_electronics_orders | B29: 7
A30: Total_fashion_orders | B30: 6
A31: Total_grocery_orders | B31: 6
A32: Orders_from_Delhi_and_Electronics | B32: 3
A33: Orders_from _Mumbai _and_ Grocery | B33: 2
A34: Orders _with_ Rating 5_and_ UPI payment | B34: 5
A35: Total_sales_from_Electronics | B35: 141097
A36: Total_sales_from_Fashion | B36: 9894
A37: Total_sales_from_grocery | B37: 34650
A38: Delhi_electronics_sales | B38: 167500
A39: Mumbai_grocery | B39: 8500
A40: Upi_payment_sales | B40: 239480
A41: A_ single _cell _containing _all _cities | B41: Delhi ,Mumbai ,Delhi ,Pune ,Delhi ,Mumbai ,Bangalore ,Delhi ,Pune ,Delhi ,Mumbai ,Bangalore ,Pune ,Delhi ,Mumbai ,Bangalore ,Delhi ,Pune ,Delhi

Sheet Manager_Data
A1: ManagerCode | B1: ManagerName | C1: Region
A2: M101 | B2: Aman Khanna | C2: North
A3: M102 | B3: Sneha Verma | C3: West
A4: M103 | B4: Rajat Malhotra | C4: Central

Sheet Cleaned_Data
A1: OrderID | B1: order | C1: id | D1: Employee name | E1: Department | F1: City | G1: Product | H1: Category | I1: Quantity | J1: Price | K1: OrderDate | L1: PaymentMode | M1: Rating | N1: ManagerCode
A2: OD101 | B2: OD | C2: 101 | D2: Rahul Sharma | E2: Electronics | F2: Delhi | G2: Laptop | H2: Electronics | I2: 2 | J2: 55000 | K2: 46034 | L2: UPI | M2: 5 | N2: M101
A3: OD102 | B3: OD | C3: 102 | D3: Priya Mehta | E3: Fashion | F3: Mumbai | G3: Tshirt | H3: Fashion | I3: 5 | J3: 799 | K3: 46037 | L3: Cash | M3: 4 | N3: M102
A4: OD103 | B4: OD | C4: 103 | D4: Amit Verma | E4: Grocery | F4: Delhi | G4: Rice Bag | H4: Grocery | I4: 3 | J4: 1200 | K4: 46040 | L4: Card | M4: 3 | N4: M103
A5: OD104 | B5: OD | C5: 104 | D5: Neha Kapoor | E5: Electronics | F5: Pune | G5: Mouse | H5: Electronics | I5: 10 | J5: 599 | K5: 46042 | L5: UPI | M5: 5 | N5: M101
A6: OD105 | B6: OD | C6: 105 | D6: Rohit Singh | E6: Fashion | F6: Delhi | G6: Jeans | H6: Fashion | I6: 4 | J6: 1899 | K6: 46044 | L6: Cash | M6: 2 | N6: M102
A7: OD106 | B7: OD | C7: 106 | D7: Karan Malhotra | E7: Grocery | F7: Mumbai | G7: Sugar | H7: Grocery | I7: 6 | J7: 450 | K7: 46047 | L7: Card | M7: 4 | N7: M103
A8: OD107 | B8: OD | C8: 107 | D8: Pooja Arora | E8: Electronics | F8: Bangalore | G8: Keyboard | H8: Electronics | I8: 7 | J8: 999 | K8: 46049 | L8: UPI | M8: 5 | N8: M101
A9: OD108 | B9: OD | C9: 108 | D9: Anjali Gupta | E9: Fashion | F9: Delhi | G9: Shoes | H9: Fashion | I9: 2 | J9: 2499 | K9: 46050 | L9: Card | M9: 4 | N9: M102
A10: OD109 | B10: OD | C10: 109 | D10: Vikas Kumar | E10: Grocery | F10: Pune | G10: Wheat | H10: Grocery | I10: 8 | J10: 950 | K10: 46052 | L10: Cash | M10: 3 | N10: M103
A11: OD110 | B11: OD | C11: 110 | D11: Riya Sharma | E11: Electronics | F11: Delhi | G11: Monitor | H11: Electronics | I11: 1 | J11: 12500 | K11: 46054 | L11: UPI | M11: 5 | N11: M101
A12: OD112 | B12: OD | C12: 112 | D12: Simran Kaur | E12: Fashion | F12: Mumbai | G12: Jacket | H12: Fashion | I12: 3 | J12: 3499 | K12: 46057 | L12: Card | M12: 4 | N12: M102
A13: OD113 | B13: OD | C13: 113 | D13: Arjun Patel | E13: Grocery | F13: Bangalore | G13: Oil | H13: Grocery | I13: 5 | J13: 1800 | K13: 46059 | L13: Cash | M13: 5 | N13: M103
... A20: OD120 | B20: OD | C20: 120 | D20: Ritika Jain | E20: Electronics | F20: Delhi | G20: Camera | H20: Electronics | I20: 1 | J20: 45000 | K20: 46071 | L20: UPI | M20: 5 | N20: M101

Sheet Raw_Data
A1: OrderID | B1: EmployeeName | C1: Department | D1: City | E1: Product | F1: Category | G1: Quantity | H1: Price | I1: OrderDate | J1: PaymentMode | K1: Rating | L1: ManagerCode
A2: OD101 | B2: Rahul sharma | C2: Electronics | D2: Delhi | E2: Laptop | F2: Electronics | G2: 2 | H2: 55000 | I2: 46034 | J2: UPI | K2: 5 | L2: M101
A3: OD102 | B3: PRIYA MEHTA | C3: Fashion | D3: Mumbai | E3: Tshirt | F3: Fashion | G3: 5 | H3: 799 | I3: 46037 | J3: Cash | K3: 4 | L3: M102
A4: OD103 | B4: amit Verma | C4: Grocery | D4: Delhi | E4: Rice Bag | F4: Grocery | G4: 3 | H4: 1200 | I4: 46040 | J4: Card | K4: 3 | L4: M103
A5: OD104 | B5: Neha Kapoor | C5: Electronics | D5: Pune | E5: Mouse | F5: Electronics | G5: 10 | H5: 599 | I5: 46042 | J5: UPI | K5: 5 | L5: M101
A6: OD105 | B6: Rohit Singh | C6: Fashion | D6: Delhi | E6: Jeans | F6: Fashion | G6: 4 | H6: 1899 | I6: 46044 | J6: Cash | K6: 2 | L6: M102
A7: OD106 | B7: Karan Malhotra | C7: Grocery | D7: Mumbai | E7: Sugar | F7: Grocery | G7: 6 | H7: 450 | I7: 46047 | J7: Card | K7: 4 | L7: M103
A8: OD107 | B8: Pooja Arora | C8: Electronics | D8: Bangalore | E8: Keyboard | F8: Electronics | G8: 7 | H8: 999 | I8: 46049 | J8: UPI | K8: 5 | L8: M101
A9: OD108 | B9: ANJALI gupta | C9: Fashion | D9: Delhi | E9: Shoes | F9: Fashion | G9: 2 | H9: 2499 | I9: 46050 | J9: Card | K9: 4 | L9: M102
A10: OD109 | B10: Vikas Kumar | C10: Grocery | D10: Pune | E10: Wheat | F10: Grocery | G10: 8 | H10: 950 | I10: 46052 | J10: Cash | K10: 3 | L10: M103
A11: OD110 | B11: Riya Sharma | C11: Electronics | D11: Delhi | E11: Monitor | F11: Electronics | G11: 1 | H11: 12500 | I11: 46054 | J11: UPI | K11: 5 | L11: M101
A12: OD111 | B12: Rahul sharma | C12: Electronics | D12: Delhi | E12: Laptop | F12: Electronics | G12: 2 | H12: 55000 | I12: 46034 | J12: UPI | K12: 5 | L12: M101
A13: OD112 | B13: Simran Kaur | C13: Fashion | D13: Mumbai | E13: Jacket | F13: Fashion | G13: 3 | H13: 3499 | I13: 46057 | J13: Card | K13: 4 | L13: M102
... A19: OD118 | B19: PRIYA MEHTA | C19: Fashion | D19: Delhi | E19: Tshirt | F19: Fashion | G19: 8 | H19: 799 | I19: 46068 | J19: Card | K19: 5 | L19: M102
A20: OD119 | B20: Nitin Arora | C20: Grocery | D20: Pune | E20: Flour | F20: Grocery | G20: 7 | H20: 850 | I20: Cash | J20: 4 | K20: M103
A21: OD120 | B21: Ritika Jain | C21: Electronics | D21: Delhi | E21: Camera | F21: Electronics | G21: 1 | H21: 45000 | I21: 46071 | J21: UPI | K21: 5 | L21: M101
